{
	"info": {
		"_postman_id": "675d56cf-313e-429c-935d-e2cd1455d071",
		"name": "Adviceslip clone",
		"schema": "https://schema.getpostman.com/json/collection/v2.1.0/collection.json",
		"_exporter_id": "37214280"
	},
	"item": [
		{
			"name": "Advice",
			"item": [
				{
					"name": "Get Random advice",
					"request": {
						"method": "GET",
						"header": [],
						"url": {
							"raw": "{{URL}}api/v1/advices",
							"host": [
								"{{URL}}api"
							],
							"path": [
								"v1",
								"advices"
							]
						}
					},
					"response": []
				},
				{
					"name": "Get Advice By ID",
					"request": {
						"method": "GET",
						"header": [],
						"url": {
							"raw": "{{URL}}api/v1/advices/3",
							"host": [
								"{{URL}}api"
							],
							"path": [
								"v1",
								"advices",
								"3"
							]
						}
					},
					"response": []
				},
				{
					"name": "Create new advice",
					"request": {
						"method": "POST",
						"header": [],
						"body": {
							"mode": "raw",
							"raw": "{\r\n    \"content\": \"Sing in the shower.\"\r\n}",
							"options": {
								"raw": {
									"language": "json"
								}
							}
						},
						"url": {
							"raw": "{{URL}}api/v1/advices",
							"host": [
								"{{URL}}api"
							],
							"path": [
								"v1",
								"advices"
							]
						}
					},
					"response": []
				}
			]
		},
		{
			"name": "Auth",
			"item": [
				{
					"name": "Signup",
					"event": [
						{
							"listen": "test",
							"script": {
								"exec": [
									"pm.environment.set(\"jwt\", pm.response.json().token);"
								],
								"type": "text/javascript",
								"packages": {}
							}
						}
					],
					"request": {
						"method": "POST",
						"header": [],
						"body": {
							"mode": "raw",
							"raw": "{\r\n    \"name\": \"test\",\r\n    \"email\": \"test@advice.com\",\r\n    \"password\": \"pass1234\",\r\n    \"passwordConfirm\": \"pass1234\"\r\n}",
							"options": {
								"raw": {
									"language": "json"
								}
							}
						},
						"url": {
							"raw": "{{URL}}api/v1/users/signup",
							"host": [
								"{{URL}}api"
							],
							"path": [
								"v1",
								"users",
								"signup"
							]
						}
					},
					"response": []
				},
				{
					"name": "Login",
					"event": [
						{
							"listen": "test",
							"script": {
								"exec": [
									"pm.environment.set(\"jwt\", pm.response.json().token);"
								],
								"type": "text/javascript",
								"packages": {}
							}
						}
					],
					"request": {
						"method": "POST",
						"header": [],
						"body": {
							"mode": "raw",
							"raw": "{\r\n    \"email\": \"admin@advice.com\",\r\n    \"password\": \"pass1234\"\r\n}",
							"options": {
								"raw": {
									"language": "json"
								}
							}
						},
						"url": {
							"raw": "{{URL}}api/v1/users/login",
							"host": [
								"{{URL}}api"
							],
							"path": [
								"v1",
								"users",
								"login"
							]
						}
					},
					"response": []
				},
				{
					"name": "Forgot Password",
					"request": {
						"method": "POST",
						"header": [],
						"body": {
							"mode": "raw",
							"raw": "{\r\n    \"email\": \"admin@advice.com\"\r\n}",
							"options": {
								"raw": {
									"language": "json"
								}
							}
						},
						"url": {
							"raw": "{{URL}}api/v1/users/forgotPassword",
							"host": [
								"{{URL}}api"
							],
							"path": [
								"v1",
								"users",
								"forgotPassword"
							]
						}
					},
					"response": []
				},
				{
					"name": "Reset Password",
					"event": [
						{
							"listen": "test",
							"script": {
								"exec": [
									"pm.environment.set(\"jwt\", pm.response.json().token);"
								],
								"type": "text/javascript",
								"packages": {}
							}
						}
					],
					"request": {
						"method": "PATCH",
						"header": [],
						"body": {
							"mode": "raw",
							"raw": "{\r\n    \"password\": \"pass1234\",\r\n    \"passwordConfirm\": \"pass1234\"\r\n}",
							"options": {
								"raw": {
									"language": "json"
								}
							}
						},
						"url": {
							"raw": "http://127.0.0.1:3000/api/v1/users/resetPassword/31f7ae89fe26fefc952b626087cc8b0e05a9afda21aef96b685fdad061fe8689",
							"protocol": "http",
							"host": [
								"127",
								"0",
								"0",
								"1"
							],
							"port": "3000",
							"path": [
								"api",
								"v1",
								"users",
								"resetPassword",
								"31f7ae89fe26fefc952b626087cc8b0e05a9afda21aef96b685fdad061fe8689"
							]
						}
					},
					"response": []
				}
			]
		},
		{
			"name": "User",
			"item": [
				{
					"name": "Update My Password",
					"event": [
						{
							"listen": "test",
							"script": {
								"exec": [
									""
								],
								"type": "text/javascript",
								"packages": {}
							}
						}
					],
					"request": {
						"auth": {
							"type": "bearer",
							"bearer": [
								{
									"key": "token",
									"value": "{{jwt}}",
									"type": "string"
								}
							]
						},
						"method": "PATCH",
						"header": [],
						"body": {
							"mode": "raw",
							"raw": "{\r\n    \"oldPassword\": \"pass1234\",\r\n    \"password\": \"pass1234\",\r\n    \"passwordConfirm\": \"pass1234\"\r\n}",
							"options": {
								"raw": {
									"language": "json"
								}
							}
						},
						"url": {
							"raw": "{{URL}}api/v1/users/updatePassword",
							"host": [
								"{{URL}}api"
							],
							"path": [
								"v1",
								"users",
								"updatePassword"
							]
						}
					},
					"response": []
				},
				{
					"name": "Get ME",
					"request": {
						"auth": {
							"type": "bearer",
							"bearer": [
								{
									"key": "token",
									"value": "{{jwt}}",
									"type": "string"
								}
							]
						},
						"method": "GET",
						"header": [],
						"url": {
							"raw": "{{URL}}api/v1/users/me",
							"host": [
								"{{URL}}api"
							],
							"path": [
								"v1",
								"users",
								"me"
							]
						}
					},
					"response": []
				},
				{
					"name": "Update Me",
					"request": {
						"auth": {
							"type": "bearer",
							"bearer": [
								{
									"key": "token",
									"value": "{{jwt}}",
									"type": "string"
								}
							]
						},
						"method": "PATCH",
						"header": [],
						"body": {
							"mode": "raw",
							"raw": "{\r\n    \"name\": \"Jawdat Samer\"\r\n}",
							"options": {
								"raw": {
									"language": "json"
								}
							}
						},
						"url": {
							"raw": "{{URL}}api/v1/users/updateMe",
							"host": [
								"{{URL}}api"
							],
							"path": [
								"v1",
								"users",
								"updateMe"
							]
						}
					},
					"response": []
				},
				{
					"name": "Delete Me",
					"request": {
						"auth": {
							"type": "bearer",
							"bearer": [
								{
									"key": "token",
									"value": "{{jwt}}",
									"type": "string"
								}
							]
						},
						"method": "DELETE",
						"header": [],
						"body": {
							"mode": "raw",
							"raw": "{\r\n    \"password\": \"pass1234\"\r\n}",
							"options": {
								"raw": {
									"language": "json"
								}
							}
						},
						"url": {
							"raw": "{{URL}}api/v1/users/deleteMe",
							"host": [
								"{{URL}}api"
							],
							"path": [
								"v1",
								"users",
								"deleteMe"
							]
						}
					},
					"response": []
				},
				{
					"name": "Get All User",
					"protocolProfileBehavior": {
						"disableBodyPruning": true
					},
					"request": {
						"auth": {
							"type": "bearer",
							"bearer": [
								{
									"key": "token",
									"value": "{{jwt}}",
									"type": "string"
								}
							]
						},
						"method": "GET",
						"header": [],
						"body": {
							"mode": "raw",
							"raw": "",
							"options": {
								"raw": {
									"language": "json"
								}
							}
						},
						"url": {
							"raw": "{{URL}}api/v1/users/",
							"host": [
								"{{URL}}api"
							],
							"path": [
								"v1",
								"users",
								""
							],
							"query": [
								{
									"key": "active",
									"value": "false",
									"disabled": true
								},
								{
									"key": "show",
									"value": "1",
									"disabled": true
								},
								{
									"key": "page",
									"value": "1",
									"disabled": true
								}
							]
						}
					},
					"response": []
				},
				{
					"name": "Get User",
					"request": {
						"auth": {
							"type": "bearer",
							"bearer": [
								{
									"key": "token",
									"value": "{{jwt}}",
									"type": "string"
								}
							]
						},
						"method": "GET",
						"header": [],
						"url": {
							"raw": "{{URL}}api/v1/users/3",
							"host": [
								"{{URL}}api"
							],
							"path": [
								"v1",
								"users",
								"3"
							]
						}
					},
					"response": []
				},
				{
					"name": "Create User",
					"request": {
						"auth": {
							"type": "bearer",
							"bearer": [
								{
									"key": "token",
									"value": "{{jwt}}",
									"type": "string"
								}
							]
						},
						"method": "POST",
						"header": [],
						"body": {
							"mode": "raw",
							"raw": "{\r\n    \"name\": \"user\",\r\n    \"email\": \"user@advice.com\",\r\n    \"password\": \"pass1234\",\r\n    \"role\": \"author\"\r\n}",
							"options": {
								"raw": {
									"language": "json"
								}
							}
						},
						"url": {
							"raw": "{{URL}}api/v1/users/",
							"host": [
								"{{URL}}api"
							],
							"path": [
								"v1",
								"users",
								""
							]
						}
					},
					"response": []
				},
				{
					"name": "Update User",
					"request": {
						"auth": {
							"type": "bearer",
							"bearer": [
								{
									"key": "token",
									"value": "{{jwt}}",
									"type": "string"
								}
							]
						},
						"method": "PATCH",
						"header": [],
						"body": {
							"mode": "raw",
							"raw": "{\r\n    \"name\": \"Sarah\",\r\n    \"active\": true\r\n}",
							"options": {
								"raw": {
									"language": "json"
								}
							}
						},
						"url": {
							"raw": "{{URL}}api/v1/users/3",
							"host": [
								"{{URL}}api"
							],
							"path": [
								"v1",
								"users",
								"3"
							]
						}
					},
					"response": []
				}
			]
		}
	]
}